MANIFEST.in
README.rst
setup.py
docs/conf.py
docs/index.rst
xbob/__init__.py
xbob.db.atnt.egg-info/PKG-INFO
xbob.db.atnt.egg-info/SOURCES.txt
xbob.db.atnt.egg-info/dependency_links.txt
xbob.db.atnt.egg-info/entry_points.txt
xbob.db.atnt.egg-info/namespace_packages.txt
xbob.db.atnt.egg-info/not-zip-safe
xbob.db.atnt.egg-info/requires.txt
xbob.db.atnt.egg-info/top_level.txt
xbob/db/__init__.py
xbob/db/atnt/__init__.py
xbob/db/atnt/driver.py
xbob/db/atnt/models.py
xbob/db/atnt/query.py
xbob/db/atnt/test.py